tests/__init__.py
tests/_test_py3_features.py
tests/mock_server.py
tests/test_features.py
tests/test_utils.py
torequests/__init__.py
torequests/__main__.py
torequests/_py3_patch.py
torequests/aiohttp_dummy.py
torequests/configs.py
torequests/crawlers.py
torequests/dummy.py
torequests/exceptions.py
torequests/logs.py
torequests/main.py
torequests/utils.py
torequests/versions.py
torequests/frequency_controller/__init__.py
torequests/frequency_controller/async_tools.py
torequests/frequency_controller/sync_tools.py
torequests-5.1.5.dist-info/LICENSE
torequests-5.1.5.dist-info/METADATA
torequests-5.1.5.dist-info/WHEEL
torequests-5.1.5.dist-info/top_level.txt
torequests-5.1.5.dist-info/RECORD
