Metadata-Version: 2.1
Name: torequests
Version: 5.1.5
Summary: Async wrapper for requests / aiohttp, and some python crawler toolkits. Let synchronization code enjoy the performance of asynchronous programming. Read more: https://github.com/ClericPy/torequests.
Home-page: https://github.com/ClericPy/torequests
Author: ClericPy
Author-email: clericpy@gmail.com
License: MIT License
Keywords: requests,async,multi-thread,aiohttp,asyncio,asynchronous
Platform: any
Classifier: License :: OSI Approved :: MIT License
Classifier: Programming Language :: Python
Classifier: Programming Language :: Python :: 2
Classifier: Programming Language :: Python :: 3
Classifier: Programming Language :: Python :: 2.7
Classifier: Programming Language :: Python :: 3.6
Classifier: Programming Language :: Python :: 3.7
Classifier: Programming Language :: Python :: 3.8
Requires-Python: >=2.7, !=3.0.*, !=3.1.*, !=3.2.*, !=3.3.*, !=3.4.*, !=3.5.*
Requires-Dist: requests
Requires-Dist: futures ; python_version < "3.1"
Requires-Dist: aiohttp (>=3.6.2) ; python_version > "3.5"
Provides-Extra: all
Requires-Dist: pyOpenSSL (>=0.14) ; extra == 'all'
Requires-Dist: cryptography (>=1.3.4) ; extra == 'all'
Requires-Dist: idna (>=2.0.0) ; extra == 'all'
Requires-Dist: PySocks (!=1.5.7,>=1.5.6) ; extra == 'all'
Requires-Dist: psutil ; extra == 'all'
Requires-Dist: pyperclip ; extra == 'all'
Provides-Extra: security
Requires-Dist: pyOpenSSL (>=0.14) ; extra == 'security'
Requires-Dist: cryptography (>=1.3.4) ; extra == 'security'
Requires-Dist: idna (>=2.0.0) ; extra == 'security'
Provides-Extra: socks
Requires-Dist: PySocks (!=1.5.7,>=1.5.6) ; extra == 'socks'
Requires-Dist: win-inet-pton ; (sys_platform == "win32" and python_version == "2.7") and extra == 'socks'
Provides-Extra: speedups
Requires-Dist: aiodns (>=1.1) ; extra == 'speedups'
Requires-Dist: Brotli ; extra == 'speedups'
Requires-Dist: cchardet ; extra == 'speedups'
